{"orderheader":[{"CustomerNumber":"AFW002","SoldTo":"AFW002Customer\n\nDel Address 1\n\nDel Address 2","ShipTo":"AFW002Customer\n\nDel Address 1\n\nDel Address 2","DocNumber":"387535","DocDate":"2024-07-05","DIMS_OrderNo":null,"strCurrency":"R","subtotal":"690.00","Total":"793.50","tax":"103.50","CustomerPastelCode":"AFW002","PaymentTerms":"30 days from invoice","InvDiscAmnt":"0","strVAT":"VAT","strSalesPerson":"101"}],"companyInfo":[{"intAutoReportID":"1","strHtmlHeader":"<strong><h6>Linx Systems cc/ ta mydimsapp</h6> \n<p>Reg No: 1234 / 1523657 / 1234 </p>\n<p>Vat Reg No: 1234567891234</p> \n<p>Company Address</p>\n<p>Company Suburb</p>\n<p>City, Province, Code</p>\n<p>Tel: 012 - 345 6789</p></strong>\n<p>Reg: 2024/03/01</p></strong>\n<p>VAT: 41252656699</p></strong>\n<p>Email: support@lsystems.co.za</p></strong>\n","Company":"Linx Demo","MainAddress":"52 Edwin Swales Rd","Suburb":"Pinetown Kloof","PhoneNo":"012 755 6662","Email":"reginald@dims.com","RegNo":"2024/78792/45","VATNO":"14578796","AccountHolder":"AccountHolder","Bank":"Absa","Branch":"Branch","BranchCode":"Brach Code","AccountNumber":"Account Number","strFormName":"HeaderFooter","dtm":"2023-03-10T20:54:30.8+05:30","intOwnerID":"1","strHtmlFooter":"<strong><p>Account Holder: Company Account Name</p>\n<p>Bank: Company Bank</p>\n<p>Branch: Bank Branch</p>\n<p>Branch Code: Bank Branch Code</p>\n<p>Account Number: Company Acc No.</p>\n<p>Ref: Please use Tax Invoice No. or your Acc. Nr as Ref.</p>\n<p>E-Mail: kyle@lsystems.co.za </p></strong><br>","strLogoPath":"images/defaultLogo.png","strQuoteMessage":null,"strDisclaimer":"<strong><p>Please note that any returns will only be accepted within 5 days of the Invoice date</p>\n<p>Signature__________________________________________Name____________________________________________Date_______________________________</p>\n<br><p>Powered by Linx Systems</p></strong>\n","strCompanyLogoName":"https://blobdigitalappfiles.blob.core.windows.net/universallogos/logo-BF.jpg"}],"orderlines":[{"OrderId":"387535","DocNumber":"ID012578","PartNumber":"11133-1","qty":"1","UnitOfMeasure":"EA","UnitPrice":"690.00","LineTax":"103.50","LineTotal":"793.50","DIMS_OrderDetailID":"1","PDesc":"COKE 1L SCH S/WATER PL. 12x1lt","LineDiscount":"0","Location":"PICKING","UserDef1":null,"UserDef2":null,"UserDef3":null,"DisplayLine":1},{"OrderId":"387545","DocNumber":null,"PartNumber":"DRC3503C-1","qty":"1","UnitOfMeasure":"EA","UnitPrice":"340.00","LineTax":"51.00","LineTotal":"391.00","DIMS_OrderDetailID":"1","PDesc":"NTSU SNUFF SMALL           12s","LineDiscount":"0","Location":"PICKING","UserDef1":null,"UserDef2":null,"UserDef3":null,"DisplayLine":2},{"OrderId":"387545","DocNumber":null,"PartNumber":"DRC3503C-1","qty":"1","UnitOfMeasure":"EA","UnitPrice":"340.00","LineTax":"51.00","LineTotal":"391.00","DIMS_OrderDetailID":"1","PDesc":"NTSU SNUFF SMALL           12s","LineDiscount":"0","Location":"PICKING","UserDef1":null,"UserDef2":null,"UserDef3":null,"DisplayLine":3},{"OrderId":"387545","DocNumber":null,"PartNumber":"DRC3503C-1","qty":"1","UnitOfMeasure":"EA","UnitPrice":"340.00","LineTax":"51.00","LineTotal":"391.00","DIMS_OrderDetailID":"1","PDesc":"NTSU SNUFF SMALL           12s","LineDiscount":"0","Location":"PICKING","UserDef1":null,"UserDef2":null,"UserDef3":null,"DisplayLine":4},{"OrderId":"387545","DocNumber":null,"PartNumber":"DRC3503C-1","qty":"1","UnitOfMeasure":"EA","UnitPrice":"340.00","LineTax":"51.00","LineTotal":"391.00","DIMS_OrderDetailID":"1","PDesc":"NTSU SNUFF SMALL           12s","LineDiscount":"0","Location":"PICKING","UserDef1":null,"UserDef2":null,"UserDef3":null,"DisplayLine":5},{"OrderId":"387545","DocNumber":null,"PartNumber":"DRC3503C-1","qty":"1","UnitOfMeasure":"EA","UnitPrice":"340.00","LineTax":"51.00","LineTotal":"391.00","DIMS_OrderDetailID":"1","PDesc":"NTSU SNUFF SMALL           12s","LineDiscount":"0","Location":"PICKING","UserDef1":null,"UserDef2":null,"UserDef3":null,"DisplayLine":6},{"OrderId":"387545","DocNumber":null,"PartNumber":"DRC3503C-1","qty":"1","UnitOfMeasure":"EA","UnitPrice":"340.00","LineTax":"51.00","LineTotal":"391.00","DIMS_OrderDetailID":"1","PDesc":"NTSU SNUFF SMALL           12s","LineDiscount":"0","Location":"PICKING","UserDef1":null,"UserDef2":null,"UserDef3":null,"DisplayLine":7},{"OrderId":"387545","DocNumber":null,"PartNumber":"DRC3503C-1","qty":"1","UnitOfMeasure":"EA","UnitPrice":"340.00","LineTax":"51.00","LineTotal":"391.00","DIMS_OrderDetailID":"1","PDesc":"NTSU SNUFF SMALL           12s","LineDiscount":"0","Location":"PICKING","UserDef1":null,"UserDef2":null,"UserDef3":null,"DisplayLine":8},{"OrderId":"387545","DocNumber":null,"PartNumber":"DRC3503C-1","qty":"1","UnitOfMeasure":"EA","UnitPrice":"340.00","LineTax":"51.00","LineTotal":"391.00","DIMS_OrderDetailID":"1","PDesc":"NTSU SNUFF SMALL           12s","LineDiscount":"0","Location":"PICKING","UserDef1":null,"UserDef2":null,"UserDef3":null,"DisplayLine":9},{"OrderId":"387545","DocNumber":null,"PartNumber":"DRC3503C-1","qty":"1","UnitOfMeasure":"EA","UnitPrice":"340.00","LineTax":"51.00","LineTotal":"391.00","DIMS_OrderDetailID":"1","PDesc":"NTSU SNUFF SMALL           12s","LineDiscount":"0","Location":"PICKING","UserDef1":null,"UserDef2":null,"UserDef3":null,"DisplayLine":10},{"OrderId":"387545","DocNumber":null,"PartNumber":"DRC3503C-1","qty":"1","UnitOfMeasure":"EA","UnitPrice":"340.00","LineTax":"51.00","LineTotal":"391.00","DIMS_OrderDetailID":"1","PDesc":"NTSU SNUFF SMALL           12s","LineDiscount":"0","Location":"PICKING","UserDef1":null,"UserDef2":null,"UserDef3":null,"DisplayLine":11},{"OrderId":"387545","DocNumber":null,"PartNumber":"DRC3503C-1","qty":"1","UnitOfMeasure":"EA","UnitPrice":"340.00","LineTax":"51.00","LineTotal":"391.00","DIMS_OrderDetailID":"1","PDesc":"NTSU SNUFF SMALL           12s","LineDiscount":"0","Location":"PICKING","UserDef1":null,"UserDef2":null,"UserDef3":null,"DisplayLine":12},{"OrderId":"387545","DocNumber":null,"PartNumber":"DRC3503C-1","qty":"1","UnitOfMeasure":"EA","UnitPrice":"340.00","LineTax":"51.00","LineTotal":"391.00","DIMS_OrderDetailID":"1","PDesc":"NTSU SNUFF SMALL           12s","LineDiscount":"0","Location":"PICKING","UserDef1":null,"UserDef2":null,"UserDef3":null,"DisplayLine":13},{"OrderId":"387545","DocNumber":null,"PartNumber":"DRC3503C-1","qty":"1","UnitOfMeasure":"EA","UnitPrice":"340.00","LineTax":"51.00","LineTotal":"391.00","DIMS_OrderDetailID":"1","PDesc":"NTSU SNUFF SMALL           12s","LineDiscount":"0","Location":"PICKING","UserDef1":null,"UserDef2":null,"UserDef3":null,"DisplayLine":14},{"OrderId":"387545","DocNumber":null,"PartNumber":"DRC3503C-1","qty":"1","UnitOfMeasure":"EA","UnitPrice":"340.00","LineTax":"51.00","LineTotal":"391.00","DIMS_OrderDetailID":"1","PDesc":"NTSU SNUFF SMALL           12s","LineDiscount":"0","Location":"PICKING","UserDef1":null,"UserDef2":null,"UserDef3":null,"DisplayLine":15},{"OrderId":"387545","DocNumber":null,"PartNumber":"DRC3503C-1","qty":"1","UnitOfMeasure":"EA","UnitPrice":"340.00","LineTax":"51.00","LineTotal":"391.00","DIMS_OrderDetailID":"1","PDesc":"NTSU SNUFF SMALL           12s","LineDiscount":"0","Location":"PICKING","UserDef1":null,"UserDef2":null,"UserDef3":null,"DisplayLine":16},{"OrderId":"387545","DocNumber":null,"PartNumber":"DRC3503C-1","qty":"1","UnitOfMeasure":"EA","UnitPrice":"340.00","LineTax":"51.00","LineTotal":"391.00","DIMS_OrderDetailID":"1","PDesc":"NTSU SNUFF SMALL           12s","LineDiscount":"0","Location":"PICKING","UserDef1":null,"UserDef2":null,"UserDef3":null,"DisplayLine":17},{"OrderId":"387545","DocNumber":null,"PartNumber":"DRC3503C-1","qty":"1","UnitOfMeasure":"EA","UnitPrice":"340.00","LineTax":"51.00","LineTotal":"391.00","DIMS_OrderDetailID":"1","PDesc":"NTSU SNUFF SMALL           12s","LineDiscount":"0","Location":"PICKING","UserDef1":null,"UserDef2":null,"UserDef3":null,"DisplayLine":18},{"OrderId":"387545","DocNumber":null,"PartNumber":"DRC3503C-1","qty":"1","UnitOfMeasure":"EA","UnitPrice":"340.00","LineTax":"51.00","LineTotal":"391.00","DIMS_OrderDetailID":"1","PDesc":"NTSU SNUFF SMALL           12s","LineDiscount":"0","Location":"PICKING","UserDef1":null,"UserDef2":null,"UserDef3":null,"DisplayLine":19},{"OrderId":"387545","DocNumber":null,"PartNumber":"DRC3503C-1","qty":"1","UnitOfMeasure":"EA","UnitPrice":"340.00","LineTax":"51.00","LineTotal":"391.00","DIMS_OrderDetailID":"1","PDesc":"NTSU SNUFF SMALL           12s","LineDiscount":"0","Location":"PICKING","UserDef1":null,"UserDef2":null,"UserDef3":null,"DisplayLine":20},{"OrderId":"387545","DocNumber":null,"PartNumber":"DRC3503C-1","qty":"1","UnitOfMeasure":"EA","UnitPrice":"340.00","LineTax":"51.00","LineTotal":"391.00","DIMS_OrderDetailID":"1","PDesc":"NTSU SNUFF SMALL           12s","LineDiscount":"0","Location":"PICKING","UserDef1":null,"UserDef2":null,"UserDef3":null,"DisplayLine":21},{"OrderId":"387545","DocNumber":null,"PartNumber":"DRC3503C-1","qty":"1","UnitOfMeasure":"EA","UnitPrice":"340.00","LineTax":"51.00","LineTotal":"391.00","DIMS_OrderDetailID":"1","PDesc":"NTSU SNUFF SMALL           12s","LineDiscount":"0","Location":"PICKING","UserDef1":null,"UserDef2":null,"UserDef3":null,"DisplayLine":22}]}